client_for3party/__init__.py
client_for3party/client.py
client_for3party/core/__init__.py
client_for3party/core/aiohttp_trace/__init__.py
client_for3party/core/aiohttp_trace/tracker.py
client_for3party-0.2.4.dist-info/METADATA
client_for3party-0.2.4.dist-info/WHEEL
client_for3party-0.2.4.dist-info/licenses/LICENSE
client_for3party-0.2.4.dist-info/RECORD
