Metadata-Version: 2.4
Name: client_for3party
Version: 0.2.4
Summary: A simple, reliable, and easy-to-debug unified client for third-party APIs
Project-URL: Homepage, https://github.com/oerlock/client_for3party
Project-URL: Issues, https://github.com/oerlock/client_for3party/issues
Author-email: Erlock Lewis <oerlock@gmail.com>
License-File: LICENSE
Classifier: License :: OSI Approved :: MIT License
Classifier: Operating System :: OS Independent
Classifier: Programming Language :: Python :: 3
Requires-Python: >=3.10
Requires-Dist: aiohttp
Requires-Dist: pydantic>=2.0.0
Provides-Extra: dev
Requires-Dist: pytest; extra == 'dev'
